kinetick/__init__.py
kinetick/algo.py
kinetick/blotter.py
kinetick/broker.py
kinetick/instrument.py
kinetick/risk_assessor.py
kinetick/workflow.py
kinetick/bot/__init__.py
kinetick/bot/dummy.py
kinetick/bot/telegram_bot.py
kinetick/enums/__init__.py
kinetick/factory/__init__.py
kinetick/factory/blotter.py
kinetick/factory/strategy.py
kinetick/lib/__init__.py
kinetick/lib/brokers/__init__.py
kinetick/lib/brokers/webull/__init__.py
kinetick/lib/brokers/webull/webull_wrapper.py
kinetick/lib/brokers/zerodha/__init__.py
kinetick/lib/brokers/zerodha/zerodha.py
kinetick/lib/indicators/__init__.py
kinetick/lib/indicators/indicators.py
kinetick/lib/indicators/supertrend.py
kinetick/lib/indicators/talib_indicators.py
kinetick/models/__init__.py
kinetick/models/contract.py
kinetick/models/ohlc.py
kinetick/models/position.py
kinetick/models/symbol.py
kinetick/models/tick.py
kinetick/strategies/__init__.py
kinetick/strategies/buy_low_sell_high.py
kinetick/strategies/macd_super_strategy.py
kinetick/tests/__init__.py
kinetick/utils/__init__.py
kinetick/utils/asynctools.py
kinetick/utils/utils.py
kinetick-1.0.15.dist-info/LICENSE
kinetick-1.0.15.dist-info/METADATA
kinetick-1.0.15.dist-info/WHEEL
kinetick-1.0.15.dist-info/entry_points.txt
kinetick-1.0.15.dist-info/top_level.txt
kinetick-1.0.15.dist-info/RECORD
