Metadata-Version: 2.1
Name: kinetick
Version: 1.0.15
Summary: Simplifying Trading
Home-page: https://github.com/imvinaypatil/kinetick
Author: vin8tech
Author-email: 
License: LGPL
Keywords: kinetick algotrading algo trading zerodha brokers stocks
Platform: any
Classifier: License :: OSI Approved :: Apache Software License
Classifier: Development Status :: 4 - Beta
Classifier: Operating System :: OS Independent
Classifier: Intended Audience :: Developers
Classifier: Topic :: Office/Business :: Financial
Classifier: Topic :: Office/Business :: Financial :: Investment
Classifier: Topic :: Software Development :: Libraries
Classifier: Topic :: Software Development :: Libraries :: Python Modules
Classifier: Programming Language :: Python :: 3.4
Classifier: Programming Language :: Python :: 3.5
Classifier: Programming Language :: Python :: 3.6
Classifier: Programming Language :: Python :: 3.7
License-File: LICENSE
Requires-Dist: python-dateutil (>=2.5.3)
Requires-Dist: numpy (==1.21.2)
Requires-Dist: pandas (==1.3.2)
Requires-Dist: pytz (>=2016.6.1)
Requires-Dist: requests (>=2.10.0)
Requires-Dist: pyzmq (>=15.2.1)
Requires-Dist: mongoengine (>=0.20.0)
Requires-Dist: python-telegram-bot (==12.7)
Requires-Dist: paho-mqtt (>=1.5.0)
Requires-Dist: TA-Lib (>=0.4.18)
Requires-Dist: webull-12 (>=2023.0.2#egg=webull)
